ubersolar/__init__.py
ubersolar/__main__.py
ubersolar/const.py
ubersolar/discovery.py
ubersolar/models.py
ubersolar/adv_parsers/__init__.py
ubersolar/adv_parsers/ubersmart.py
ubersolar/devices/__init__.py
ubersolar/devices/device.py
ubersolar/devices/ubersmart.py
pyUbersolar-0.1.3.dist-info/LICENSE
pyUbersolar-0.1.3.dist-info/METADATA
pyUbersolar-0.1.3.dist-info/WHEEL
pyUbersolar-0.1.3.dist-info/top_level.txt
pyUbersolar-0.1.3.dist-info/RECORD
